aetherml_settings/__init__.py
aetherml_settings/configs.py
aetherml_settings/database/db_config.py
aetherml_settings/elastic_search_config/__init__.py
aetherml_settings/elastic_search_config/embedding_mapping.py
aetherml_settings/elastic_search_config/es_conn.py
aetherml_settings/elastic_search_config/parallel_config.py
aetherml_settings/llm/embedder.py
aetherml_settings/model/dto/es_property_dto.py
aetherml_settings/model/dto/es_property_search.py
aetherml_settings/model/dto/property_dto.py
aetherml_settings/model/dto/sql.py
aetherml_settings/model/dto/user_dto.py
aetherml_settings/model/entity/__init__.py
aetherml_settings/model/entity/base.py
aetherml_settings/model/entity/es_property.py
aetherml_settings/model/entity/property.py
aetherml_settings/model/entity/users.py
aetherml_settings-0.1.1.dist-info/METADATA
aetherml_settings-0.1.1.dist-info/WHEEL
aetherml_settings-0.1.1.dist-info/RECORD
