Metadata-Version: 2.1
Name: aetherml-settings
Version: 0.1.1
Summary: 
Author: aetherml
Requires-Python: >=3.10,<4.0
Classifier: Programming Language :: Python :: 3
Classifier: Programming Language :: Python :: 3.10
Classifier: Programming Language :: Python :: 3.11
Classifier: Programming Language :: Python :: 3.12
Classifier: Programming Language :: Python :: 3.13
Requires-Dist: alembic (>=1.15.2,<2.0.0)
Requires-Dist: elasticsearch (>=9.0.1,<10.0.0)
Requires-Dist: psycopg-binary (>=3.2.9,<4.0.0)
Requires-Dist: pydantic (>=2.11.5,<3.0.0)
Requires-Dist: python-dotenv (>=1.1.0,<2.0.0)
Requires-Dist: sqlalchemy (>=2.0.41,<3.0.0)
